{
  "swagger" : "2.0",
  "info" : {
    "description" : "Loan application API.",
    "version" : "1.0.0",
    "title" : "Loan application API",
    "contact" : {
      "email" : "developers@qred.com"
    },
    "license" : {
      "name" : "Apache 2.0",
      "url" : "http://www.apache.org/licenses/LICENSE-2.0.html"
    }
  },
  "tags" : [ {
    "name" : "developers",
    "description" : "Operations available to regular developers"
  } ],
  "paths" : {
    "/loans/v1/applications" : {
      "post" : {
        "tags" : [ "developers" ],
        "summary" : "adds an application",
        "operationId" : "addApplication",
        "description" : "Adds an loan application to the system",
        "consumes" : [ "application/json" ],
        "produces" : [ "application/json" ],
        "parameters" : [ {
          "in" : "body",
          "name" : "application",
          "description" : "Application to add",
          "schema" : {
            "$ref" : "#/definitions/ApplicationRequest"
          }
        } ],
        "responses" : {
          "201" : {
            "description" : "item created",
            "schema" : {
              "$ref" : "#/definitions/ApplicationCreateResponse"
            }
          },
          "400" : {
            "description" : "invalid input, object invalid",
            "schema" : {
              "type" : "array",
              "items" : {
                "$ref" : "#/definitions/ApplicationErrorResponse"
              }
            }
          }
        }
      }
    },
    "/loans/v1/applications/{id}" : {
      "get" : {
        "tags" : [ "developers" ],
        "parameters" : [ {
          "name" : "id",
          "in" : "path",
          "description" : "The id of the application",
          "required" : true,
          "type" : "string"
        } ],
        "produces" : [ "application/json" ],
        "responses" : {
          "200" : {
            "description" : "search results matching criteria",
            "schema" : {
              "$ref" : "#/definitions/Application"
            }
          }
        }
      }
    }
  },
  "definitions" : {
    "ApplicationRequest" : {
      "required" : [ "amount", "organization", "applicant" ],
      "properties" : {
        "amount" : {
          "type" : "number",
          "example" : 15000.0
        },
        "purposeOfLoan" : {
          "type" : "string",
          "example" : "I need to increase liquidity due to upcoming costs associated with participation in branch conference"
        },
        "organization" : {
          "$ref" : "#/definitions/ApplicationOrganization"
        },
        "applicant" : {
          "$ref" : "#/definitions/ApplicationApplicant"
        },
        "files" : {
          "type" : "array",
          "items" : {
            "$ref" : "#/definitions/UploadBase64File"
          }
        }
      }
    },
    "MonetaryAmount" : {
      "properties" : {
        "currency" : {
          "type" : "string",
          "example" : "USD",
          "description" : "The currency in which the monetary amount is expressed. Use standard ISO 4217 currency format e.g. \"USD\""
        },
        "value" : {
          "type" : "number",
          "example" : 100000,
          "description" : "The amount in the specified currency"
        }
      }
    },
    "ApplicationErrorResponse" : {
      "properties" : {
        "property" : {
          "type" : "string",
          "example" : "amount"
        },
        "description" : {
          "type" : "string",
          "example" : "Amount is a required field"
        }
      }
    },
    "ApplicationApplicant" : {
      "required" : [ "email", "telephone" ],
      "properties" : {
        "email" : {
          "type" : "string",
          "format" : "email",
          "example" : "joe.smith@a-company.com"
        },
        "telephone" : {
          "type" : "string",
          "example" : "408-867-5309",
          "description" : "The telephone number."
        },
        "taxID" : {
          "type" : "string",
          "example" : "197012012344",
          "description" : "The Tax / Fiscal ID of the person, e.g. the TIN in the US or the CIF/NIF in Spain. For Denmark that would be CPR."
        },
        "givenName" : {
          "type" : "string",
          "example" : "Joe",
          "description" : "Given name. In the U.S., the first name of a Person. This can be used along with familyName instead of the name property."
        },
        "additionalName" : {
          "type" : "string",
          "example" : "Daniels",
          "description" : "An additional name for a Person, can be used for a middle name."
        },
        "familyName" : {
          "type" : "string",
          "example" : "Smith",
          "description" : "Family name. In the U.S., the last name of an Person. This can be used along with givenName instead of the name property."
        }
      }
    },
    "ApplicationOrganization" : {
      "required" : [ "taxID" ],
      "properties" : {
        "taxID" : {
          "type" : "string",
          "example" : "SE2344473928",
          "description" : "Same as vatID in Sweden"
        },
        "legalName" : {
          "type" : "string",
          "example" : "A-company AB"
        },
        "type" : {
          "$ref" : "#/definitions/BusinessOrganizationType"
        },
        "email" : {
          "type" : "string",
          "format" : "email",
          "example" : "contact@a-company.com"
        },
        "telephone" : {
          "type" : "string",
          "example" : "408-867-5309",
          "description" : "The telephone number."
        },
        "url" : {
          "type" : "string",
          "example" : "http://www.a-company.com",
          "description" : "Url to the organization site."
        },
        "lastYearsTurnover" : {
          "$ref" : "#/definitions/MonetaryAmount"
        }
      }
    },
    "BusinessOrganizationType" : {
      "type" : "string",
      "enum" : [ "SoleProprietorship", "Partnership", "Corporation", "LimitedLiabilityCompany", "Cooperative" ]
    },
    "ApplicationCreateResponse" : {
      "properties" : {
        "id" : {
          "type" : "string",
          "example" : "APP-32444"
        },
        "url" : {
          "type" : "string",
          "example" : "https://api.qred.com/loans/v1/applications/APP-32444"
        }
      }
    },
    "ApplicationDecision" : {
      "type" : "string",
      "example" : "Maybe",
      "enum" : [ "Accepted", "Denied", "Maybe" ]
    },
    "Application" : {
      "properties" : {
        "decision" : {
          "$ref" : "#/definitions/ApplicationDecision"
        }
      }
    },
    "UploadBase64File" : {
      "properties" : {
        "encodingFormat" : {
          "type" : "array",
          "items" : {
            "type" : "string"
          },
          "example" : [ "application/xml", "https//api.a-company.com/transactions/v1" ],
          "description" : "Media type typically expressed using a MIME format (see [IANA](http://www.iana.org/assignments/media-types/media-types.xhtml) site and [MDN reference](https://developer.mozilla.org/en-US/docs/Web/HTTP/Basics_of_HTTP/MIME_types)) e.g. application/zip for a SoftwareApplication binary, audio/mpeg for .mp3 etc.).\nUnregistered or niche encoding and file formats can be indicated instead via the most appropriate URL, e.g. defining Web page or a Wikipedia/Wikidata entry. In the case of organization specific file format with a specific purpose that could be a url to schema definition. For instance, transaction data format defined by `a-company` (see the example) that may or may not be hosted at that url."
        },
        "filename" : {
          "type" : "string",
          "example" : "company-specific-format.xml"
        },
        "base64Content" : {
          "type" : "string",
          "example" : "4530987p9257493875243098572398057432095",
          "description" : "Base64 encoded binary content."
        }
      }
    }
  },
  "schemes" : [ "https" ],
  "host" : "virtserver.swaggerhub.com",
  "basePath" : "/qredab/loan-api-partner/1.0.0"
}